deepseek_ocr_encoder/__init__.py
deepseek_ocr_encoder/encoder.py
deepseek_ocr_encoder-1.0.1.dist-info/METADATA
deepseek_ocr_encoder-1.0.1.dist-info/WHEEL
deepseek_ocr_encoder-1.0.1.dist-info/licenses/LICENSE
deepseek_ocr_encoder-1.0.1.dist-info/RECORD
