Metadata-Version: 2.4
Name: deepseek-ocr-encoder
Version: 1.0.1
Summary: A handy and elastic encoder for DeepSeek OCR vision tasks
Project-URL: Homepage, https://github.com/dwojcik92/deepseek-ocr-encoder
Project-URL: Repository, https://github.com/dwojcik92/deepseek-ocr-encoder
Project-URL: Issues, https://github.com/dwojcik92/deepseek-ocr-encoder/issues
Project-URL: Documentation, https://github.com/dwojcik92/deepseek-ocr-encoder#readme
Author-email: Dariusz Wojcik <dariusz.patryk.wojcik@gmail.com>
License: MIT
License-File: LICENSE
Keywords: clip,deepseek,deepseek-ocr,huggingface,ocr,pytorch,sam,transformers,vision-encoder
Classifier: Development Status :: 3 - Alpha
Classifier: Intended Audience :: Developers
Classifier: Intended Audience :: Science/Research
Classifier: License :: OSI Approved :: MIT License
Classifier: Programming Language :: Python :: 3
Classifier: Programming Language :: Python :: 3.10
Classifier: Programming Language :: Python :: 3.11
Classifier: Programming Language :: Python :: 3.12
Classifier: Topic :: Scientific/Engineering :: Artificial Intelligence
Requires-Python: >=3.12
Requires-Dist: addict>=2.4.0
Requires-Dist: easydict==1.13
Requires-Dist: einops==0.8.1
Requires-Dist: packaging>=20.0
Requires-Dist: pillow>=9.0.0
Requires-Dist: pymupdf>=1.23.0
Requires-Dist: torch>=2.8.0
Requires-Dist: torchvision>=0.15.0
Requires-Dist: transformers<4.48.0,>=4.30.0
Provides-Extra: dev
Requires-Dist: black>=23.0.0; extra == 'dev'
Requires-Dist: mypy>=1.0.0; extra == 'dev'
Requires-Dist: pytest>=7.0.0; extra == 'dev'
Requires-Dist: ruff>=0.1.0; extra == 'dev'
